lampylib/__init__.py
lampylib/__main__.py
lampylib/lib.py
lampylib-0.1.1.dist-info/entry_points.txt
lampylib-0.1.1.dist-info/LICENSE
lampylib-0.1.1.dist-info/WHEEL
lampylib-0.1.1.dist-info/METADATA
lampylib-0.1.1.dist-info/RECORD
