Metadata-Version: 2.1
Name: lampylib
Version: 0.1.1
Summary: Launchpad Mini python library
Home-page: https://github.com/pkulev/lampy
License: MIT
Keywords: launchpad,midi
Author: Pavel Kulyov
Author-email: kulyov.pavel@gmail.com
Requires-Python: >=3.7,<4.0
Classifier: Development Status :: 3 - Alpha
Classifier: Intended Audience :: Developers
Classifier: Intended Audience :: Education
Classifier: Intended Audience :: End Users/Desktop
Classifier: License :: OSI Approved :: MIT License
Classifier: Natural Language :: English
Classifier: Operating System :: POSIX :: Linux
Classifier: Programming Language :: Python :: 3
Classifier: Programming Language :: Python :: 3.7
Classifier: Programming Language :: Python :: Implementation :: CPython
Requires-Dist: python-rtmidi
Project-URL: Repository, https://github.com/pkulev/lampy
